pompy/__init__.py
pompy/demos.py
pompy/models.py
pompy/processors.py
pompy-0.1.1.dist-info/LICENSE
pompy-0.1.1.dist-info/METADATA
pompy-0.1.1.dist-info/WHEEL
pompy-0.1.1.dist-info/top_level.txt
pompy-0.1.1.dist-info/RECORD
