Metadata-Version: 2.1
Name: pompy
Version: 0.1.1
Summary: Puff-based odour plume model
Home-page: https://github.com/InsectRobotics/pompy
Author: Matt Graham
License: MIT
Project-URL: Documentation, https://pompy-docs.readthedocs.io/en/latest/
Keywords: simulation plume navigation
Platform: UNKNOWN
Classifier: Programming Language :: Python :: 2
Classifier: Programming Language :: Python :: 2.7
Classifier: Programming Language :: Python :: 3
Classifier: Programming Language :: Python :: 3.4
Classifier: Programming Language :: Python :: 3.5
Classifier: Programming Language :: Python :: 3.6
Classifier: Programming Language :: Python :: 3.7
Classifier: License :: OSI Approved :: MIT License
Classifier: Topic :: Scientific/Engineering
Classifier: Intended Audience :: Science/Research
Classifier: Operating System :: OS Independent
Requires-Dist: numpy
Requires-Dist: scipy
Requires-Dist: matplotlib
